{
    "$id": "https://raw.githubusercontent.com/dell/DellRedfishSchemas/refs/heads/main/iDRAC/DellStorage.json",
    "$schema": "http://redfish.dmtf.org/schemas/v1/redfish-schema-v1.json",
    "copyright": "Copyright 2014-2025 Dell, Inc. or its subsidiaries. All Rights Reserved.",
    "definitions": {
        "ControllerDrivesDecommission": {
            "anyOf": [
                {
                    "$ref": "https://raw.githubusercontent.com/dell/DellRedfishSchemas/refs/heads/main/iDRAC/DellStorage.v1_0_0.json#/definitions/ControllerDrivesDecommission"
                }
            ],
            "description": "This action is used to decommission the drives attached to the storage controller.",
            "longDescription": "This action is used to decommission the drives attached to the storage controller."
        }
    },
    "title": "#DellStorage"
}