{
    "$id": "https://raw.githubusercontent.com/dell/DellRedfishSchemas/refs/heads/main/iDRACEthernetInterface.v1_0_0.json",
    "$schema": "http://redfish.dmtf.org/schemas/v1/redfish-schema-v1.json",
    "copyright": "Copyright 2014-2025 Dell, Inc. or its subsidiaries. All Rights Reserved.",
    "definitions": {
        "DellEthernetInterface": {
            "additionalProperties": false,
            "description": "This property shall represent Oem properties for EthernetInterface resource .",
            "longDescription": "This property shall represent Oem properties for EthernetInterface resource.",
            "patternProperties": {
                "^([a-zA-Z_][a-zA-Z0-9_]*)?@(odata|Redfish|Message)\\.[a-zA-Z_][a-zA-Z0-9_]*$": {
                    "description": "This property shall specify a valid odata or Redfish property.",
                    "type": [
                        "array",
                        "boolean",
                        "integer",
                        "number",
                        "null",
                        "object",
                        "string"
                    ]
                }
            },
            "properties": {
                "DHCPv4Server": {
                    "description": "DHCPv4 server for this interface.",
                    "longDescription": "This property shall contain the DHCPv4 server for this interface.",
                    "readonly": true,
                    "type": [
                        "string",
                        "null"
                    ]
                },
                "DHCPv6Server": {
                    "description": "DHCPv6 server for this interface.",
                    "longDescription": "This property shall contain the DHCPv6 server for this interface.",
                    "readonly": true,
                    "type": [
                        "string",
                        "null"
                    ]
                },
                "InterfaceStatus": {
                    "anyOf": [
                        {
                            "$ref": "#/definitions/InterfaceStatus"
                        },
                        {
                            "type": "null"
                        }
                    ],
                    "description": "The status of the interface.",
                    "longDescription": "This property shall contain the status of the interface.",
                    "readonly": true
                },
                "InterfaceType": {
                    "anyOf": [
                        {
                            "$ref": "#/definitions/InterfaceType"
                        },
                        {
                            "type": "null"
                        }
                    ],
                    "description": "The type of the interface.",
                    "longDescription": "This property shall contain the type of the interface.",
                    "readonly": true
                }
            },
            "type": "object"
        },
        "InterfaceStatus": {
            "enum": [
                "Down",
                "Up",
                "Testing",
                "Unknown",
                "Dormant",
                "Absent"
            ],
            "enumDescriptions": {
                "Absent": "Interface status is absent.",
                "Dormant": "Interface status is dormant.",
                "Down": "Interface status is down.",
                "Testing": "Interface status is testing.",
                "Unknown": "Interface status is unknown.",
                "Up": "Interface status is up."
            },
            "type": "string"
        },
        "InterfaceType": {
            "enum": [
                "Ethernet",
                "Loop Back",
                "Token Ring",
                "Ppp",
                "Atm",
                "IEEE 802.11",
                "Tunnel",
                "IEEE 1IEEE 802.11",
                "Other"
            ],
            "enumDescriptions": {
                "Atm": "Atm interface.",
                "Ethernet": "Ethernet interface.",
                "IEEE 1IEEE 802.11": "IEEE 1IEEE 802.11 interface.",
                "IEEE 802.11": "IEEE 802.11 interface.",
                "Loop Back": "Loop Back interface.",
                "Other": "Other interface.",
                "Ppp": "Ppp interface.",
                "Token Ring": "Token ring interface.",
                "Tunnel": "Tunnel interface."
            },
            "type": "string"
        }
    },
    "owningEntity": "Dell",
    "title": "#DellEthernetInterface.v1_0_0"
}